[
    {
      "id": 4,
      "finished": "finished",
      "prize_money": "$15,000",
      "entry_fee": "$120",
      "duration": "3 weeks",
      "title": "Fall Finale Trading Tournament"
    },
    {
      "id": 5,
      "finished": "finished",
      "prize_money": "$25,000",
      "entry_fee": "$200",
      "duration": "1 month",
      "title": "September Showdown Trading Challenge"
    },
    {
      "id": 6,
      "finished": "finished",
      "prize_money": "$40,000",
      "entry_fee": "$250",
      "duration": "2 months",
      "title": "Summer Sizzle Stock Trading Contest"
    },
    {
      "id": 7,
      "finished": "finished",
      "prize_money": "$20,000",
      "entry_fee": "$150",
      "duration": "4 weeks",
      "title": "Spring Fling Trading Extravaganza"
    },
    {
      "id": 8,
      "finished": "finished",
      "prize_money": "$30,000",
      "entry_fee": "$180",
      "duration": "6 weeks",
      "title": "Winter Windfall Trading Championship"
    },
    {
      "id": 9,
      "finished": "finished",
      "prize_money": "$50,000",
      "entry_fee": "$300",
      "duration": "2 months",
      "title": "Holiday High-Stakes Stock Trading Showdown"
    }
  ]
  